{
	"genericName": "Venetian Trade",
	"description": ".",
	"cost": {
		"food": 200,
		"wood": 500,
		"stone": 0,
		"metal": 200
	},
	"requirements": { "tech": "byza/economy_reform" },
	"requirementsTooltip": "Unlocked with Economic Reforms (Bouleterion).",
	"icon": "friendship.png",
	"researchTime": 40,
	"tooltip": "Merchant Ships +25% trade profit per trip.",
	"modifications": [{"value": "Trader/GainMultiplier", "multiply": 1.25}],
	"affects": ["MerchantShip"],
	"soundComplete": "interface/alarm/alarm_upgradearmory.xml"
}
